geopipeline/__init__.py
geopipeline/__main__.py
geopipeline/cli.py
geopipeline/science_planning.py
geopipeline/setup.py
geopipeline/time.py
geopipeline/geometry/__init__.py
geopipeline/geometry/derived.py
geopipeline/geometry/finder.py
geopipeline/geometry/support.py
geopipeline/models/__init__.py
geopipeline/models/magnetic_field.py
juice_geopipeline-0.6.1.dist-info/METADATA
juice_geopipeline-0.6.1.dist-info/WHEEL
juice_geopipeline-0.6.1.dist-info/entry_points.txt
juice_geopipeline-0.6.1.dist-info/top_level.txt
juice_geopipeline-0.6.1.dist-info/RECORD
