Metadata-Version: 2.1
Name: juice-geopipeline
Version: 0.6.1
Author: Marc Costa
Author-email: marc.costa@ext.esa.int
License: MIT
Classifier: Programming Language :: Python :: 3.6
Requires-Python: >=3.6
Requires-Dist: planetary-coverage
Requires-Dist: python-dotenv
Requires-Dist: pandas
Requires-Dist: matplotlib
Requires-Dist: pytest
Requires-Dist: numpy
Requires-Dist: PyAstronomy
Requires-Dist: astroquery
Provides-Extra: dev
Requires-Dist: autoflake ; extra == 'dev'
Requires-Dist: black ; extra == 'dev'
Requires-Dist: flake8 ; extra == 'dev'
Requires-Dist: flake8-bugbear ; extra == 'dev'
Requires-Dist: flake8-builtins ; extra == 'dev'
Requires-Dist: flake8-comprehensions ; extra == 'dev'
Requires-Dist: flake8-debugger ; extra == 'dev'
Requires-Dist: flake8-eradicate ; extra == 'dev'
Requires-Dist: isort ; extra == 'dev'
Requires-Dist: mkdocs-material ; extra == 'dev'
Requires-Dist: mypy ; extra == 'dev'
Requires-Dist: pep8-naming ; extra == 'dev'
Requires-Dist: pre-commit ; extra == 'dev'
Requires-Dist: pymdown-extensions ; extra == 'dev'
Requires-Dist: pytest ; extra == 'dev'
Requires-Dist: pytest-github-actions-annotate-failures ; extra == 'dev'
Requires-Dist: pytest-cov ; extra == 'dev'
Requires-Dist: python-kacl ; extra == 'dev'
Requires-Dist: pyupgrade ; extra == 'dev'
Requires-Dist: tryceratops ; extra == 'dev'
Requires-Dist: twine ; extra == 'dev'
Requires-Dist: mkdocstrings >=0.18 ; (python_version >= "3.9") and extra == 'dev'
